{"sheet":[[{"row":0,"col":0,"data":"wesh alors"},{"row":0,"col":1,"data":"Hello salut c'est trop cool ce truc de folie"},null,null,{"row":0,"col":4,"data":"12"}],[{"row":1,"col":0,"data":""},{"row":1,"col":1,"data":"Hello salut c'est trop cool ce truc de folie"},null,null,{"row":1,"col":4,"data":"13"}],[null,{"row":2,"col":1,"data":"Hello salut c'est trop cool ce truc de folie"},null,null,{"row":2,"col":4,"data":"1+1"}],[null,{"row":3,"col":1,"data":""}],[null,{"row":4,"col":1,"data":"Hello salut c'est trop cool ce truc de folie"}],[null,{"row":5,"col":1,"data":"Hello salut c'est trop cool ce truc de folie"}],[null,{"row":6,"col":1,"data":"Hello salut c'est trop cool ce truc de folie"}],[null,{"row":7,"col":1,"data":"Hello salut c'est trop cool ce truc de folie"}],[null,{"row":8,"col":1,"data":"Hello salut c'est trop cool ce truc de folie"}],[{"row":9,"col":0,"data":""},null,{"row":9,"col":2,"data":""}],[null,null,null,null,null,{"row":10,"col":5,"data":"Coucou"}],[],[null,{"row":12,"col":1,"data":"YO"}],[],[],[null,{"row":15,"col":1,"data":"YO YO"}],[],[],[],[],[],[],[null,null,null,null,null,null,null,null,null,null,null,null,null,null,null,null,null,null,null,null,{"row":22,"col":20,"data":""}]]}